pdf_compression/__init__.py
pdf_compression/compress_pdf.py
tests/__init__.py
tests/test_empty.py
tests/test_nonexisting.py
tests/test_nonpdf.py
tests/test_protected_with_pass.py
tests/test_protected_with_wrong_pass.py
tests/test_protected_without_pass.py
tests/test_with_outfile.py
tests/test_without_outfile.py
pdf_compression-0.1.1.dist-info/METADATA
pdf_compression-0.1.1.dist-info/WHEEL
pdf_compression-0.1.1.dist-info/top_level.txt
pdf_compression-0.1.1.dist-info/RECORD
